asteroid/__init__.py
asteroid/binarize.py
asteroid/complex_nn.py
asteroid/metrics.py
asteroid/separate.py
asteroid/data/__init__.py
asteroid/data/avspeech_dataset.py
asteroid/data/dampvsep_dataset.py
asteroid/data/dns_dataset.py
asteroid/data/fuss_dataset.py
asteroid/data/kinect_wsj.py
asteroid/data/librimix_dataset.py
asteroid/data/musdb18_dataset.py
asteroid/data/sms_wsj_dataset.py
asteroid/data/utils.py
asteroid/data/vad_dataset.py
asteroid/data/wham_dataset.py
asteroid/data/whamr_dataset.py
asteroid/data/wsj0_mix.py
asteroid/dsp/__init__.py
asteroid/dsp/beamforming.py
asteroid/dsp/consistency.py
asteroid/dsp/deltas.py
asteroid/dsp/normalization.py
asteroid/dsp/overlap_add.py
asteroid/dsp/spatial.py
asteroid/dsp/vad.py
asteroid/engine/__init__.py
asteroid/engine/optimizers.py
asteroid/engine/schedulers.py
asteroid/engine/system.py
asteroid/losses/__init__.py
asteroid/losses/bark_matrix_16k.mat
asteroid/losses/bark_matrix_8k.mat
asteroid/losses/cluster.py
asteroid/losses/mixit_wrapper.py
asteroid/losses/mse.py
asteroid/losses/multi_scale_spectral.py
asteroid/losses/pit_wrapper.py
asteroid/losses/pmsqe.py
asteroid/losses/sdr.py
asteroid/losses/sinkpit_wrapper.py
asteroid/losses/soft_f1.py
asteroid/losses/stoi.py
asteroid/masknn/__init__.py
asteroid/masknn/_dccrn_architectures.py
asteroid/masknn/_dcunet_architectures.py
asteroid/masknn/_local.py
asteroid/masknn/activations.py
asteroid/masknn/attention.py
asteroid/masknn/base.py
asteroid/masknn/convolutional.py
asteroid/masknn/norms.py
asteroid/masknn/recurrent.py
asteroid/masknn/tac.py
asteroid/models/__init__.py
asteroid/models/base_models.py
asteroid/models/conv_tasnet.py
asteroid/models/dccrnet.py
asteroid/models/dcunet.py
asteroid/models/demask.py
asteroid/models/dprnn_tasnet.py
asteroid/models/dptnet.py
asteroid/models/fasnet.py
asteroid/models/lstm_tasnet.py
asteroid/models/publisher.py
asteroid/models/sudormrf.py
asteroid/models/x_umx.py
asteroid/models/zenodo.py
asteroid/scripts/__init__.py
asteroid-0.7.0.dist-info/LICENSE
asteroid-0.7.0.dist-info/METADATA
asteroid-0.7.0.dist-info/WHEEL
asteroid-0.7.0.dist-info/entry_points.txt
asteroid-0.7.0.dist-info/top_level.txt
asteroid-0.7.0.dist-info/RECORD
