Metadata-Version: 2.1
Name: asteroid
Version: 0.7.0
Summary: PyTorch-based audio source separation toolkit
Home-page: https://github.com/asteroid-team/asteroid
Author: Manuel Pariente
Author-email: manuel.pariente@loria.fr
License: MIT
Classifier: Development Status :: 4 - Beta
Classifier: Programming Language :: Python :: 3
Classifier: Programming Language :: Python :: 3.8
Classifier: Programming Language :: Python :: 3.9
Classifier: Programming Language :: Python :: 3.10
Classifier: License :: OSI Approved :: MIT License
Classifier: Operating System :: OS Independent
Requires-Python: >=3.6
License-File: LICENSE
Requires-Dist: numpy (>=1.16.4)
Requires-Dist: scipy (>=1.10.1)
Requires-Dist: torch (>=2.0.0)
Requires-Dist: asteroid-filterbanks (>=0.4.0)
Requires-Dist: SoundFile (>=0.10.2)
Requires-Dist: huggingface-hub (>=0.0.2)
Requires-Dist: PyYAML (>=5.0)
Requires-Dist: pandas (>=0.23.4)
Requires-Dist: pytorch-lightning (>=2.0.0)
Requires-Dist: torchmetrics (<=0.11.4)
Requires-Dist: torchaudio (>=0.5.0)
Requires-Dist: pb-bss-eval (>=0.0.2)
Requires-Dist: torch-stoi (>=0.1.2)
Requires-Dist: torch-optimizer (<0.2.0,>=0.0.1a12)
Requires-Dist: julius
